README.md
setup.cfg
setup.py
archives/__init__.py
archives/archives.py
archives/globals.py
archives.egg-info/PKG-INFO
archives.egg-info/SOURCES.txt
archives.egg-info/dependency_links.txt
archives.egg-info/entry_points.txt
archives.egg-info/not-zip-safe
archives.egg-info/requires.txt
archives.egg-info/top_level.txt
archives/models/__init__.py
archives/models/python.py
archives/models/rules.py
archives/models/tags.py
archives/rules/__init__.py
archives/utils/__init__.py
archives/utils/files.py
archives/utils/state.py
archives/utils/text.py
tests/__init__.py
tests/conftest.py
tests/test_archives.py