Metadata-Version: 2.1
Name: archives
Version: 0.11
Summary: a new way to do python code documentation
Home-page: https://github.com/jpetrucciani/archives.git
Author: Jacobi Petrucciani
Author-email: jacobi@mimirhq.com
License: MIT
Download-URL: https://github.com/jpetrucciani/archives.git
Platform: UNKNOWN
Classifier: Programming Language :: Python :: 3
Classifier: Programming Language :: Python :: 3.6
Classifier: Programming Language :: Python :: 3.7
Classifier: Programming Language :: Python :: 3.8
Classifier: Programming Language :: Python :: Implementation :: CPython
Classifier: Programming Language :: Python :: Implementation :: PyPy
